definit/__init__.py
definit/dag/__init__.py
definit/dag/dag.py
definit/db/__init__.py
definit/db/interface.py
definit/db/md.py
definit/definition/__init__.py
definit/definition/definition.py
definit/definition/definition_key.py
definit/definition/field.py
definit-0.5.0.dist-info/METADATA
definit-0.5.0.dist-info/WHEEL
definit-0.5.0.dist-info/top_level.txt
definit-0.5.0.dist-info/RECORD
