Metadata-Version: 2.4
Name: definit
Version: 0.5.0
Summary: Hierarchy of precise definitions.
Requires-Python: >=3.12
Provides-Extra: dev
Requires-Dist: pytest; extra == "dev"
Requires-Dist: import-linter==2.9; extra == "dev"
